yuio/__init__.py
yuio/_typing.py
yuio/_typing_ext.py
yuio/_version.py
yuio/app.py
yuio/cli.py
yuio/color.py
yuio/complete.py
yuio/config.py
yuio/dbg.py
yuio/doc.py
yuio/exec.py
yuio/git.py
yuio/hl.py
yuio/io.py
yuio/json_schema.py
yuio/md.py
yuio/parse.py
yuio/py.typed
yuio/rst.py
yuio/secret.py
yuio/string.py
yuio/term.py
yuio/theme.py
yuio/ty.py
yuio/util.py
yuio/widget.py
yuio/_complete/complete.bash
yuio/_complete/complete.fish
yuio/_complete/complete.ps1
yuio/_complete/complete.zsh
yuio/_complete/complete_init.ps1
yuio/_dist/__init__.py
yuio/_dist/dsu.py
yuio/_dist/typing_extensions.py
yuio/ext/__init__.py
yuio/ext/sphinx/__init__.py
yuio/ext/sphinx/autodoc.py
yuio/ext/sphinx/directives.py
yuio/ext/sphinx/domain.py
yuio/ext/sphinx/roles.py
yuio/ext/sphinx/setup.py
yuio/ext/sphinx/utils.py
yuio/scripts/__init__.py
yuio/scripts/showkey.py
yuio-2.0.1.dist-info/licenses/LICENSE
yuio-2.0.1.dist-info/METADATA
yuio-2.0.1.dist-info/WHEEL
yuio-2.0.1.dist-info/top_level.txt
yuio-2.0.1.dist-info/RECORD
