Metadata-Version: 2.4
Name: yuio
Version: 2.0.1
Summary: Lite and user-friendly CLI library
Author-email: Tamika Nomara <taminomara@gmail.com>
License-Expression: MIT
Project-URL: Documentation, https://yuio.readthedocs.io/
Project-URL: Issues, https://github.com/taminomara/yuio/issues
Project-URL: Source, https://github.com/taminomara/yuio/
Project-URL: Changelog, https://github.com/taminomara/yuio/blob/main/CHANGELOG.md
Classifier: Development Status :: 5 - Production/Stable
Classifier: Programming Language :: Python :: 3
Classifier: Programming Language :: Python :: 3 :: Only
Classifier: Programming Language :: Python :: 3.10
Classifier: Programming Language :: Python :: 3.11
Classifier: Programming Language :: Python :: 3.12
Classifier: Programming Language :: Python :: 3.13
Classifier: Programming Language :: Python :: 3.14
Classifier: Topic :: Software Development :: Libraries :: Python Modules
Classifier: Topic :: Software Development :: User Interfaces
Classifier: Topic :: System :: Logging
Classifier: Intended Audience :: Developers
Classifier: Environment :: Console
Classifier: Typing :: Typed
Requires-Python: >=3.10
License-File: LICENSE
Requires-Dist: typing-extensions<5,>=4.13
Dynamic: license-file
